Workbook

Sheet Header
A1: HEADER — Dashboard Title & PM
A2: Field | B2: Value
A3: Dashboard Title | B3: WESTERN & SOUTHERN REGION SDCC PROJECT DASHBOARD | PE-286
A4: Project Code | B4: PE-286
A5: Region | B5: Western & SOUTHERN Region
A6: Project Manager | B6: Hany Kamal

Sheet General_Info
A1: GENERAL INFO — Key Project Dates
A2: Field | B2: Date | C2: Notes
A3: Contract Sign Date | B3: 45497
A4: Madinah Handover | B4: 45530
A5: Abha Handover | B5: 45571
A6: Jizan Handover | B6: 45718
A7: Jeddah / Makkah HO | B7: 45830
A8: Contractual TCC | B8: 46227 | C8: Highlighted orange in dashboard
A9: Expected TCC | B9: 46435 | C9: Highlighted red in dashboard — delayed

Sheet Commercial_Info
A1: COMMERCIAL INFO (SAR)
A2: Field | B2: Value (SAR) | C2: Tag / Badge | D2: Notes
A3: Org. Contract Value | B3: 388016486
A4: Cont. Adv. Payment | B4: 0
A5: Change Orders | B5: 0
A6: Sub. Cost Claim | B6: 0
A7: Expected Cont. Value | B7: 388016486 | D7: Equals Org. Contract Value + Change Orders
A8: Org. Contingency | B8: 34426811
A9: Rem. Contingency | B9: 15596872 | C9: =B9/B8 -> 0.45304434 | D9: Badge shown in amber/red in dashboard

Sheet Budgetary_Info
A1: BUDGETARY INFO
A2: Field | B2: Value | C2: Tag / Badge | D2: Notes
A3: Rev. Budget Amount | B3: 355587125 | D3: SAR
A4: Target POC 2026 | B4: 100% | D4: Percentage
A5: Planned POC | B5: 0.688
A6: Actual POC Till Date | B6: 0.409 | D6: Red in dashboard; badge shows gap vs target
A7: Org. Contingency | B7: 34426811 | D7: SAR
A8: Rem. Contingency | B8: 15596872 | D8: SAR
A9: Contingency Used | B9: =(B7-B8)/B7 -> 0.54695566 | D9: Amber in dashboard
A10: EOT Status | B10: Submitted | D10: Red in dashboard

Sheet Collection_Info
A1: COLLECTION INFO (SAR)
A2: Field | B2: Value (SAR) | C2: Tag % | D2: Color in Dashboard | E2: Notes
A3: Invoiceable Amount | B3: 204059236 | C3: =B3/Commercial_Info!$B$3 -> 0.52590352 | D3: Green
A4: Submitted Invoices | B4: 152961744 | C4: =B4/Commercial_Info!$B$3 -> 0.39421455 | D4: Amber
A5: Approved Invoices | B5: 152961744 | C5: =B5/Commercial_Info!$B$3 -> 0.39421455 | D5: Amber
A6: Collected Adv. | B6: 0 | D6: Normal
A7: Col. Amount Inc Adv | B7: 68039022 | C7: =B7/Commercial_Info!$B$3 -> 0.17535085 | D7: Amber
A8: Billing vs Actual POC | B8: =ROUNDUP(C4*100,0)&"%"&" / "&ROUNDUP(Budgetary_Info!B6*100,0)&"%" -> 40% / 41% | D8: Normal | E8: Text field — shown as-is

Sheet Cash_Flow
A1: CASH FLOW STATUS (SAR Millions)
A2: Field | B2: Value (SAR M) | C2: Bar Width % | D2: Notes
A3: Net Cash Position | B3: =B5-B6 -> -61.2 | D3: Shown as hero figure; red background
A4: Hero Sub-label | B4: Outflow exceeds inflow · negative position | D4: Descriptive text under the big number
A5: Cash In | B5: 68 | C5: =(B5/B6)*100 -> 52.631579 | D5: Green bar; relative to Cash Out (max)
A6: Cash Out | B6: 129.2 | C6: 100% | D6: Orange bar; this is the 100% reference

Sheet Manpower
A1: MANPOWER STATUS
A2: A — Totals
A3: Field | B3: Value | C3: Notes
A4: Total Manpower | B4: =B5+B6 -> 751 | C4: Hero figure — orange background
A5: Direct Labor | B5: 654 | C5: Green segment in donut
A6: Indirect | B6: 97 | C6: Orange segment in donut
A7: Direct Share % | B7: =B5/B4 -> 0.87083888 | C7: Shown as green text
A9: B — Direct Labor Breakdown
A10: Category | B10: Count | C10: Notes
A11: ALF (Alfanar direct) | B11: 386 | C11: Shown as sub-label under Direct Labor
A12: SC (Subcontractor) | B12: 268 | C12: Shown as sub-label under Direct Labor
A14: C — Donut Chart SVG Parameters (auto-calculated from counts above)
A15: Parameter | B15: Value | C15: Formula / Notes
A16: Direct % of Total | B16: =B4/B5*100 -> 114.8318 | C16: e.g. 79.6 → used for green arc dasharray
A17: Indirect % of Total | B17: =B6/B5*100 -> 14.831804 | C17: e.g. 20.4 → used for orange arc dasharray
A18: Green arc dasharray part1 | B18: =B16 -> 114.8318 | C18: stroke-dasharray first value (green)
A19: Green arc dasharray part2 | B19: =100-B16 -> -14.831804 | C19: stroke-dasharray second value (green)
A20: Orange arc dasharray part1 | B20: =B17 -> 14.831804 | C20: stroke-dasharray first value (orange)
A21: Orange arc dasharray part2 | B21: =100-B17 -> 85.168196 | C21: stroke-dasharray second value (orange)

Sheet Project_Phases
A1: PROJECT PHASES — Plan vs Actual (%)
A2: Phase | B2: Plan % | C2: Actual % | D2: Delta | E2: Delta Color | F2: Notes
A3: Overall | B3: 92.78 | C3: 84.28 | D3: =-C3+B3 -> 8.5 | E3: warn | F3: Red badge
A4: Engineering | B4: 100 | C4: 99.25 | D4: =-C4+B4 -> 0.75 | E4: good | F4: Green badge
A5: Equipment | B5: 100 | C5: 95.54 | D5: =-C5+B5 -> 4.46 | E5: mild | F5: Amber badge
A6: Construction | B6: 95.92 | C6: 90.82 | D6: =-C6+B6 -> 5.1 | E6: warn | F6: Red badge
A7: Installation | B7: 100 | C7: 93.32 | D7: =-C7+B7 -> 6.68 | E7: mild | F7: Amber badge
A8: Testing & Commissioning | B8: 68.05 | C8: 22.08 | D8: =-C8+B8 -> 45.97 | E8: warn | F8: Red badge; actual bar uses tiny style

Sheet City_Progress
A1: PROGRESS PER CITY — Plan vs Actual (%)
A2: City | B2: Plan % | C2: Actual % | D2: Delta | E2: Delta Color | F2: Notes
A3: Madinah | B3: 92.88 | C3: 83.78 | D3: =-C3+B3 -> 9.1 | E3: warn
A4: Abha | B4: 92.15 | C4: 84.33 | D4: =-C4+B4 -> 7.82 | E4: mild
A5: Jizan | B5: 90.96 | C5: 81.37 | D5: =-C5+B5 -> 9.59 | E5: warn | F5: Trails plan the most
A6: Jeddah | B6: 95.89 | C6: 86.1 | D6: =-C6+B6 -> 9.79 | E6: warn
A7: Makkah | B7: 95.71 | C7: 91.03 | D7: =-C7+B7 -> 4.68 | E7: mild | F7: Leads on actual completion
A8: Footer Note (italic text shown below chart)

Sheet Timeline
A1: PROJECTS TIMELINE — Monthly Milestones
A2: Month Label | B2: Has Milestone | C2: Milestone Text | D2: Flag Position | E2: Is TCC Cell | F2: TCC Box Label | G2: TCC Box Date | H2: Notes
A3: 45620 | B3: YES | C3: Project Start | D3: above | E3: NO | H3: First month
A4: 45650 | B4: NO | E4: NO
A5: 45681 | B5: NO | E5: NO
A6: 45712 | B6: NO | E6: NO
A7: 45740 | B7: YES | C7: MADINAH P.C. | D7: above | E7: NO
A8: 45771 | B8: YES | C8: ABHA P.C. | D8: below | E8: NO | H8: Flag goes below bar
A9: 45801 | B9: NO | E9: NO
A10: 45832 | B10: YES | C10: JIZAN P.C. | D10: above | E10: NO
A11: 45862 | B11: NO | E11: NO
A12: 45893 | B12: NO | E12: NO
A13: 45924 | B13: YES | C13: MAD& ABH Structur Completed | D13: below | E13: NO
A14: 45954 | B14: YES | C14: Jizan Structure Completed | D14: above | E14: NO
A15: 45985 | B15: NO | E15: NO
A16: 46015 | B16: YES | C16: CET Equip. Delivery | D16: below | E16: NO
A17: 46046 | B17: NO | E17: NO
A18: 46077 | B18: NO | E18: NO
A19: 46105 | B19: NO | E19: NO
A20: 46136 | B20: NO | E20: NO
A21: 46166 | B21: NO | E21: NO
A22: 46197 | B22: NO | E22: YES
A23: 46227 | B23: NO | E23: YES | F23: Contractual TCC | G23: 24-Jul-26 | H23: Orange cell
A24: 46258 | B24: NO | E24: NO
A25: 46289 | B25: NO | E25: NO
A26: 46319 | B26: NO | E26: NO
A27: 46350 | B27: NO | E27: NO
A28: 46380 | B28: NO | E28: NO
A29: 46411 | B29: NO | E29: NO
A30: 46442 | B30: NO | E30: YES | F30: Revised TCC | G30: 46435 | H30: Red cell

Sheet Major_Issues
A1: MAJOR ISSUES STATUS
A2: # | B2: Issue Description | C2: Trade | D2: Entity | E2: Required Action | F2: Priority
A3: 1 | B3: Delay Delivery of Low Current 3rd Fix Materials | C3: Procurement | D3: Supplier (Digital Era) | E3: PM to arrange a meeting with supplier top management to enhance the current delivery forecast dates to meet the TCC contractual date. | F3: High
A4: 2 | B4: Delay Approval of Jockey Pumps (Fire Pumps Package) | C4: Engineering / Procurement | D4: SE | E4: SE to expedite the approval of Jockey Pumps to start manufacturing of materials and fulfill the supplied flow USA. | F4: High
A5: 3 | B5: Delay Approval of LAN/WAN (M6 Routers) Which Fulfill Contract Requirements | C5: Engineering / Procurement | D5: SE | E5: Approved design is to use (M14 routers), delivery duration 20–24 weeks.SE to approve Alfanar proposal to deliver (M6 routers) which have a delivery duration of 6–8 weeks. | F5: High
A6: 4 | B6: Delay Delivery of DWDM (PO Issued to AES) – Waiting for Final Confirmation of Recent Traffic Plan | C6: Engineering / Procurement | D6: SE | E6: SE to expedite providing the confirmed recent traffic plan to start manufacturing materials of DWDM. | F6: High

Sheet Equipment_Status
A1: EQUIPMENT STATUS
A2: # | B2: Equipment | C2: Vendor | D2: PO | E2: GAFM | F2: FAT | G2: Delivery | H2: Status
A3: 1 | B3: ADMS/DERMS Servers | C3: CET | D3: Issued | E3: 1 | F3: 1 | G3: 1 | H3: OK
A4: 2 | B4: CRAC / PACU Units | C4: Zamil | D4: Issued | E4: 1 | F4: 1 | G4: 1 | H4: OK
A5: 3 | B5: FM-200 Cylinders | C5: Zamil | D5: Issued | E5: 1 | F5: 1 | G5: 1 | H5: OK
A6: 4 | B6: DDC Panels | C6: Marine | D6: Issued | E6: 1 | F6: 1 | G6: 1 | H6: OK
A7: 5 | B7: AC/DC Panels | C7: AES | D7: Issued | E7: 1 | F7: 0.9 | G7: 0.9 | H7: Delayed
A8: 6 | B8: 48 VDC System | C8: AES | D8: Issued | E8: 1 | F8: 0 | G8: 0 | H8: Delayed
A9: 7 | B9: Fire Pumps | C9: Zamil | D9: Issued | E9: 0.8 | F9: 0 | G9: 0 | H9: Delayed
A10: 8 | B10: Security System | C10: ITC | D10: Issued | E10: 1 | F10: N/A | G10: 0.15 | H10: Delayed

Sheet Footer
A1: FOOTER — Classification & Branding
A2: Field | B2: Value
A3: Classification | B3: Public
A4: Prepared Date | B4: 46176
A5: Department | B5: Control Center
A6: Brand Name | B6: alfanar
